Metadata-Version: 1.1
Name: cebstemmer
Version: 1.6
Summary: A Cebuano Stemmer based on Krovetz Algorithm
Home-page: https://github.com/ajrequina/Cebuano-Stemmer
Author: Arjemariel Requina
Author-email: rjrequina@gmail.com
License: UNKNOWN
Download-URL: https://github.com/ajrequina/Cebuano-Stemmer/archive/1.0.tar.gz
Keywords: stemmer,cebuano-stemmer
Platform: UNKNOWN
